ga4gh/core/__init__.py
ga4gh/core/digests.py
ga4gh/core/enderef.py
ga4gh/core/identifiers.py
ga4gh/core/models.py
ga4gh/core/pydantic.py
ga4gh/vrs/__init__.py
ga4gh/vrs/dataproxy.py
ga4gh/vrs/enderef.py
ga4gh/vrs/models.py
ga4gh/vrs/normalize.py
ga4gh/vrs/extras/__init__.py
ga4gh/vrs/extras/decorators.py
ga4gh/vrs/extras/object_store.py
ga4gh/vrs/extras/translator.py
ga4gh/vrs/extras/annotator/__init__.py
ga4gh/vrs/extras/annotator/cli.py
ga4gh/vrs/extras/annotator/vcf.py
ga4gh/vrs/utils/__init__.py
ga4gh/vrs/utils/hgvs_tools.py
ga4gh_vrs-2.1.4.dist-info/licenses/LICENSE
ga4gh_vrs-2.1.4.dist-info/METADATA
ga4gh_vrs-2.1.4.dist-info/WHEEL
ga4gh_vrs-2.1.4.dist-info/entry_points.txt
ga4gh_vrs-2.1.4.dist-info/top_level.txt
ga4gh_vrs-2.1.4.dist-info/RECORD
