Metadata-Version: 2.4
Name: ga4gh.vrs
Version: 2.1.4
Summary: GA4GH Variation Representation Specification (VRS) reference implementation
Author-email: Larry Babb <lbabb@broadinstitute.org>, Reece Hart <reecehart@gmail.com>, Andreas Prlic <andreas.prlic@gmail.com>, Alex Wagner <alex.wagner@nationwidechildrens.org>
License: 
Project-URL: Homepage, https://github.com/ga4gh/vrs-python
Project-URL: Documentation, https://github.com/ga4gh/vrs-python
Project-URL: Changelog, https://github.com/ga4gh/vrs-python/releases
Project-URL: Source, https://github.com/ga4gh/vrs-python
Project-URL: Bug Tracker, https://github.com/ga4gh/vrs-python/issues
Keywords: bioinformatics,ga4gh,genomics,hgvs,spdi,variation
Classifier: Development Status :: 3 - Alpha
Classifier: Intended Audience :: Developers
Classifier: Intended Audience :: Healthcare Industry
Classifier: Intended Audience :: Science/Research
Classifier: License :: OSI Approved :: Apache Software License
Classifier: Operating System :: OS Independent
Classifier: Programming Language :: Python
Classifier: Programming Language :: Python :: 3
Classifier: Programming Language :: Python :: 3.10
Classifier: Programming Language :: Python :: 3.11
Classifier: Programming Language :: Python :: 3.12
Classifier: Programming Language :: Python :: 3.13
Classifier: Topic :: Scientific/Engineering :: Bio-Informatics
Classifier: Topic :: Scientific/Engineering :: Medical Science Apps.
Requires-Python: >=3.10
License-File: LICENSE
Requires-Dist: pydantic~=2.1
Requires-Dist: bioutils
Requires-Dist: requests
Requires-Dist: canonicaljson
Requires-Dist: setuptools>=78.1.0
Requires-Dist: typing-extensions
Provides-Extra: extras
Requires-Dist: psycopg2-binary; extra == "extras"
Requires-Dist: biocommons.seqrepo>=0.5.1; extra == "extras"
Requires-Dist: bioutils>=0.5.2; extra == "extras"
Requires-Dist: hgvs<1.5.5,>=1.4; extra == "extras"
Requires-Dist: dill~=0.3.7; extra == "extras"
Requires-Dist: click; extra == "extras"
Requires-Dist: pysam==0.23.0; extra == "extras"
Provides-Extra: dev
Requires-Dist: pytest; extra == "dev"
Requires-Dist: pytest-cov; extra == "dev"
Requires-Dist: pytest-vcr; extra == "dev"
Requires-Dist: vcrpy>=7.0.0; extra == "dev"
Requires-Dist: pyyaml; extra == "dev"
Requires-Dist: pre-commit>=4.0.1; extra == "dev"
Requires-Dist: ruff==0.9.4; extra == "dev"
Requires-Dist: sphinx; extra == "dev"
Requires-Dist: sphinx_rtd_theme; extra == "dev"
Provides-Extra: notebooks
Requires-Dist: jupyter; extra == "notebooks"
Requires-Dist: tabulate; extra == "notebooks"
Requires-Dist: pyyaml; extra == "notebooks"
Dynamic: license-file
